lib_log_utils/__init__.py
lib_log_utils/__init__conf__.py
lib_log_utils/lib_log_utils.py
lib_log_utils/lib_log_utils_cli.py
lib_log_utils/log_config.py
lib_log_utils/log_handlers.py
lib_log_utils/log_levels.py
lib_log_utils/log_traceback.py
lib_log_utils/py.typed
lib_log_utils-1.4.15.dist-info/LICENSE
lib_log_utils-1.4.15.dist-info/METADATA
lib_log_utils-1.4.15.dist-info/WHEEL
lib_log_utils-1.4.15.dist-info/entry_points.txt
lib_log_utils-1.4.15.dist-info/top_level.txt
lib_log_utils-1.4.15.dist-info/RECORD
