Metadata-Version: 2.1
Name: lib-log-utils
Version: 1.4.15
Summary: colored log messages and banners from commandline and python
Author-email: Robert Nowotny <bitranox@gmail.com>
License: MIT
Project-URL: Homepage, https://github.com/bitranox/lib_log_utils
Project-URL: Documentation, https://github.com/bitranox/lib_log_utils/blob/master/README.rst
Project-URL: Repository, https://github.com/bitranox/lib_log_utils.git
Project-URL: Changelog, https://github.com/bitranox/lib_log_utils/blob/master/CHANGES.rst
Classifier: Development Status :: 5 - Production/Stable
Classifier: Intended Audience :: Developers
Classifier: License :: OSI Approved :: MIT License
Classifier: Natural Language :: English
Classifier: Operating System :: OS Independent
Classifier: Programming Language :: Python
Classifier: Topic :: Software Development :: Libraries :: Python Modules
Requires-Python: >=3.8.0
License-File: LICENSE
Requires-Dist: click
Requires-Dist: coloredlogs
Requires-Dist: cli-exit-tools
Requires-Dist: lib-parameter
Requires-Dist: lib-platform
Requires-Dist: lib-programname
Provides-Extra: test
Requires-Dist: black ; extra == 'test'
Requires-Dist: codecov ; extra == 'test'
Requires-Dist: coloredlogs ; extra == 'test'
Requires-Dist: coverage ; extra == 'test'
Requires-Dist: flake8 ; extra == 'test'
Requires-Dist: mypy ; extra == 'test'
Requires-Dist: pytest ; extra == 'test'
Requires-Dist: pytest-cov ; extra == 'test'
Requires-Dist: pytest-runner ; extra == 'test'
Requires-Dist: readme-renderer ; extra == 'test'
